kimp/cli.py
kimp/modules/GitManager.py
kimp-0.1.6.dist-info/METADATA
kimp-0.1.6.dist-info/WHEEL
kimp-0.1.6.dist-info/entry_points.txt
kimp-0.1.6.dist-info/RECORD
