Metadata-Version: 2.3
Name: kimp
Version: 0.1.6
Summary: Kimera package manager using GitHub as the registry
Author: marin
Author-email: catalin@orson.ro
Requires-Python: >=3.10,<4.0
Classifier: Programming Language :: Python :: 3
Classifier: Programming Language :: Python :: 3.10
Classifier: Programming Language :: Python :: 3.11
Classifier: Programming Language :: Python :: 3.12
Classifier: Programming Language :: Python :: 3.13
Requires-Dist: click (>=8.1,<9.0)
Requires-Dist: gitpython (>=3.1,<4.0)
Requires-Dist: requests (>=2.31,<3.0)
Requires-Dist: rich (>=13.7,<14.0)
Requires-Dist: tomlkit (>=0.13.2,<0.14.0)
